{"content": {"suites": {"0": {"status": {"total_pass": 0, "total_skip": 0, "total_xpass": 0, "total_xfail": 0, "total_rerun": 0, "total_fail": 1, "total_error": 0}, "tests": {"0": {"status": "FAIL", "message": "   selenium.common.exceptions.NoSuchElementException: Message: no such element: Unable to locate element: {\"method\":\"xpath\",\"selector\":\"//div[contains(@class, 'MuiFormControl-root')][1]//input\"}\n     (Session info: chrome=120.0.6099.224); For documentation on this error, please visit: https://www.selenium.dev/documentation/webdriver/troubleshooting/errors#no-such-element-exception\n   Stacktrace:\n   #0 0x5600c997cf83 <unknown>\n   #1 0x5600c9635cf7 <unknown>\n   #2 0x5600c968599e <unknown>\n   #3 0x5600c9685aa1 <unknown>\n   #4 0x5600c96d0d64 <unknown>\n   #5 0x5600c96af0dd <unknown>\n   #6 0x5600c96ce006 <unknown>\n   #7 0x5600c96aee53 <unknown>\n   #8 0x5600c9676dd4 <unknown>\n   #9 0x5600c96781de <unknown>\n   #10 0x5600c9941531 <unknown>\n   #11 0x5600c9945455 <unknown>\n   #12 0x5600c992df55 <unknown>\n   #13 0x5600c99460ef <unknown>\n   #14 0x5600c991199f <unknown>\n   #15 0x5600c996a008 <unknown>\n   #16 0x5600c996a1d7 <unknown>\n   #17 0x5600c997c124 <unknown>\n   #18 0x7ff72cc94ac3 <unknown>\n", "test_name": "test_occurrences_open", "rerun": "0"}}, "suite_name": "test_dashboard.py"}}}, "date": "February 23, 2024", "start_time": 1708705218.653513, "total_suite": 1, "status": "FAIL", "status_list": {"pass": "0", "fail": "1", "skip": "0", "error": "0", "xpass": "0", "xfail": "0", "rerun": "0"}, "total_tests": "1"}